yaml_source_map/__init__.py
yaml_source_map/errors.py
yaml_source_map/handle.py
yaml_source_map/test.yaml
yaml_source_map/types.py
yaml_source_map-1.0.1.dist-info/LICENSE
yaml_source_map-1.0.1.dist-info/WHEEL
yaml_source_map-1.0.1.dist-info/METADATA
yaml_source_map-1.0.1.dist-info/RECORD
